{
  "project_info": {
    "project_number": "988890426286",
    "firebase_url": "https://project-3078675154276937782.firebaseio.com",
    "project_id": "project-3078675154276937782",
    "storage_bucket": "project-3078675154276937782.appspot.com"
  },
  "client": [
    {
      "client_info": {
        "mobilesdk_app_id": "1:988890426286:android:362f22c98e029e05e7363f",
        "android_client_info": {
          "package_name": "com.video.test1"
        }
      },
      "oauth_client": [
        {
          "client_id": "988890426286-tqeemajhciate4u7ietpq45n2602mr8c.apps.googleusercontent.com",
          "client_type": 3
        }
      ],
      "api_key": [
        {
          "current_key": "AIzaSyA8q7UnptEZmfgEISr4x_ClruPPt3_YAUw"
        }
      ],
      "services": {
        "appinvite_service": {
          "other_platform_oauth_client": [
            {
              "client_id": "988890426286-tqeemajhciate4u7ietpq45n2602mr8c.apps.googleusercontent.com",
              "client_type": 3
            },
            {
              "client_id": "988890426286-ejkk9n0avteoubq73v8m9na6u4uvv99o.apps.googleusercontent.com",
              "client_type": 2,
              "ios_info": {
                "bundle_id": "com.lk.lktest3"
              }
            }
          ]
        }
      }
    },
    {
      "client_info": {
        "mobilesdk_app_id": "1:988890426286:android:6cff8c29737c54bce7363f",
        "android_client_info": {
          "package_name": "com.video.test2"
        }
      },
      "oauth_client": [
        {
          "client_id": "988890426286-tqeemajhciate4u7ietpq45n2602mr8c.apps.googleusercontent.com",
          "client_type": 3
        }
      ],
      "api_key": [
        {
          "current_key": "AIzaSyA8q7UnptEZmfgEISr4x_ClruPPt3_YAUw"
        }
      ],
      "services": {
        "appinvite_service": {
          "other_platform_oauth_client": [
            {
              "client_id": "988890426286-tqeemajhciate4u7ietpq45n2602mr8c.apps.googleusercontent.com",
              "client_type": 3
            },
            {
              "client_id": "988890426286-ejkk9n0avteoubq73v8m9na6u4uvv99o.apps.googleusercontent.com",
              "client_type": 2,
              "ios_info": {
                "bundle_id": "com.lk.lktest3"
              }
            }
          ]
        }
      }
    },
    {
      "client_info": {
        "mobilesdk_app_id": "1:988890426286:android:97d807333ee35e90e7363f",
        "android_client_info": {
          "package_name": "com.video.test3"
        }
      },
      "oauth_client": [
        {
          "client_id": "988890426286-tqeemajhciate4u7ietpq45n2602mr8c.apps.googleusercontent.com",
          "client_type": 3
        }
      ],
      "api_key": [
        {
          "current_key": "AIzaSyA8q7UnptEZmfgEISr4x_ClruPPt3_YAUw"
        }
      ],
      "services": {
        "appinvite_service": {
          "other_platform_oauth_client": [
            {
              "client_id": "988890426286-tqeemajhciate4u7ietpq45n2602mr8c.apps.googleusercontent.com",
              "client_type": 3
            },
            {
              "client_id": "988890426286-ejkk9n0avteoubq73v8m9na6u4uvv99o.apps.googleusercontent.com",
              "client_type": 2,
              "ios_info": {
                "bundle_id": "com.lk.lktest3"
              }
            }
          ]
        }
      }
    }
  ],
  "configuration_version": "1"
}